<PAMDataset>
  <PAMRasterBand band="1">
    <Histograms>
      <HistItem>
        <HistMin>-44</HistMin>
        <HistMax>104</HistMax>
        <BucketCount>256</BucketCount>
        <IncludeOutOfRange>1</IncludeOutOfRange>
        <Approximate>0</Approximate>
        <HistCounts>1|0|0|2|0|0|0|0|0|0|0|0|0|1|0|2|0|0|0|0|0|0|1|0|1|1|0|1|0|0|0|1|1|0|2|0|0|1|0|3|0|5|0|6|7|0|6|0|8|12|0|9|0|30|0|25|57|0|68|0|131|0|257|553|0|1386|0|3839|10425|0|33957|0|108312|0|146737|5060622|0|287107|0|254923|252954|0|237171|0|214254|0|191977|173542|0|159016|0|146308|0|135315|125479|0|119393|0|117721|115800|0|113230|0|109437|0|104624|98029|0|90923|0|85350|79769|0|76704|0|75829|0|76552|77474|0|78937|0|81427|0|84849|89575|0|94079|0|99281|104338|0|110155|0|115292|0|119597|123332|0|126087|0|127134|0|128187|127181|0|124752|0|122322|120359|0|118377|0|115698|0|111888|107481|0|103016|0|96798|91884|0|87387|0|82446|0|78619|75047|0|70667|0|66678|0|62056|58392|0|56358|0|54066|50920|0|49063|0|46847|0|44350|40761|0|38031|0|35473|33627|0|31905|0|30332|0|27809|25328|0|23070|0|20561|0|18617|17579|0|16261|0|15033|14019|0|13377|0|12561|0|11402|10072|0|8848|0|7388|6219|0|5151|0|4187|0|3110|2373|0|1536|0|929|0|549|286|0|190|0|117|75|0|68|0|33|0|26|15|0|7|0|2|0|1</HistCounts>
      </HistItem>
    </Histograms>
    <Metadata>
      <MDI key="STATISTICS_MINIMUM">-44</MDI>
      <MDI key="STATISTICS_MAXIMUM">104</MDI>
      <MDI key="STATISTICS_MEAN">17.275817657184</MDI>
      <MDI key="STATISTICS_STDDEV">21.885955334237</MDI>
      <MDI key="STATISTICS_MEDIAN">4.752941</MDI>
      <MDI key="STATISTICS_COUNT">12967201.000000</MDI>
      <MDI key="STATISTICS_SKIPFACTORX">1</MDI>
      <MDI key="STATISTICS_SKIPFACTORY">1</MDI>
      <MDI key="STATISTICS_EXCLUDEDVALUES"></MDI>
      <MDI key="STATISTICS_COVARIANCES">478.9950408922226</MDI>
    </Metadata>
  </PAMRasterBand>
</PAMDataset>
